one_ring/__init__.py
one_ring/asyncio_sugar.py
one_ring/csp.py
one_ring/nursery.py
one_ring-0.1.1.dist-info/METADATA
one_ring-0.1.1.dist-info/WHEEL
one_ring-0.1.1.dist-info/top_level.txt
one_ring-0.1.1.dist-info/RECORD
